gbmtsplits/__init__.py
gbmtsplits/_version.py
gbmtsplits/cli.py
gbmtsplits/clustering.py
gbmtsplits/plot.py
gbmtsplits/split.py
gbmtsplits/logs/__init__.py
gbmtsplits/logs/config.py
gbmtsplits-0.0.8.dist-info/LICENSE
gbmtsplits-0.0.8.dist-info/METADATA
gbmtsplits-0.0.8.dist-info/WHEEL
gbmtsplits-0.0.8.dist-info/top_level.txt
gbmtsplits-0.0.8.dist-info/RECORD
