Metadata-Version: 2.1
Name: gbmtsplits
Version: 0.0.8
Summary: A tool to create well-balanced data splits for multi-task learning
Author-email: Sohvi Luukkonen <s.luukkonen@lacdr.leidenuniv.nl>
License: GNU GENERAL PUBLIC LICENSE
Keywords: data split,multi-task,balanced data
Classifier: Development Status :: 5 - Production/Stable
Classifier: License :: OSI Approved :: MIT License
Classifier: Programming Language :: Python :: 3.10
Classifier: Programming Language :: Python :: 3.9
Classifier: Programming Language :: Python :: 3.8
Classifier: Programming Language :: Python :: 3.7
License-File: LICENSE
Requires-Dist: parameterized
Requires-Dist: matplotlib
Requires-Dist: seaborn
Requires-Dist: pandas
Requires-Dist: scikit-learn
Requires-Dist: rdkit
Requires-Dist: numpy
Requires-Dist: tqdm
Requires-Dist: pulp
